Metadata-Version: 1.2
Name: magi
Version: 0.0.12
Summary: high level wrapper for parallel univariate time series forecasting
Home-page: http://github.com/DavisTownsend/forecast
Author: Davis Townsend
Author-email: dtownsend@ea.com
License: MIT
Keywords: time series analysis forecast forecasting predict model parallel
Platform: UNKNOWN
Classifier: Development Status :: 2 - Pre-Alpha
Classifier: License :: OSI Approved :: MIT License
Classifier: Programming Language :: Python :: 3.5
Classifier: Programming Language :: Python :: 3.6
Requires-Python: ~=3.5
